geosun_base/GeosunBaseTransformLib8.cp310-win_amd64.pyd
geosun_base/GeosunBaseTransformLib8.cp311-win_amd64.pyd
geosun_base/GeosunBaseTransformLib8.cp312-win_amd64.pyd
geosun_base/GeosunBaseTransformLib8.cp313-win_amd64.pyd
geosun_base/GeosunBaseTransformLib8.cp314-win_amd64.pyd
geosun_base/GeosunBaseTransformLib8.cp39-win_amd64.pyd
geosun_base/GeosunBaseTransformLib8.pyi
geosun_base/__init__.py
geosun_base/py.typed
geosun_base-0.2.0.dist-info/METADATA
geosun_base-0.2.0.dist-info/WHEEL
geosun_base-0.2.0.dist-info/top_level.txt
geosun_base-0.2.0.dist-info/RECORD
